{
  "classTimes": [
    {
      "fullQualifiedName": "org.jsoup.parser.XmlTreeBuilderTest",
      "timeInMs": 5387
    },
    {
      "fullQualifiedName": "org.jsoup.helper.DataUtilTest",
      "timeInMs": 4711
    },
    {
      "fullQualifiedName": "org.jsoup.nodes.ElementTest",
      "timeInMs": 164074
    },
    {
      "fullQualifiedName": "org.jsoup.nodes.DocumentTest",
      "timeInMs": 48709
    },
    {
      "fullQualifiedName": "org.jsoup.parser.HtmlParserTest",
      "timeInMs": 19690
    },
    {
      "fullQualifiedName": "org.jsoup.parser.AttributeParseTest",
      "timeInMs": 3591
    },
    {
      "fullQualifiedName": "org.jsoup.nodes.EntitiesTest",
      "timeInMs": 5653
    },
    {
      "fullQualifiedName": "org.jsoup.parser.TokeniserTest",
      "timeInMs": 297387
    },
    {
      "fullQualifiedName": "org.jsoup.safety.CleanerTest",
      "timeInMs": 8847
    },
    {
      "fullQualifiedName": "org.jsoup.nodes.NodeTest",
      "timeInMs": 46015
    },
    {
      "fullQualifiedName": "org.jsoup.select.SelectorTest",
      "timeInMs": 8404
    },
    {
      "fullQualifiedName": "org.jsoup.select.ElementsTest",
      "timeInMs": 5747
    },
    {
      "fullQualifiedName": "org.jsoup.integration.ConnectTest",
      "timeInMs": 12884
    },
    {
      "fullQualifiedName": "org.jsoup.select.CssTest",
      "timeInMs": 5484
    },
    {
      "fullQualifiedName": "org.jsoup.nodes.FormElementTest",
      "timeInMs": 16931
    },
    {
      "fullQualifiedName": "org.jsoup.select.TraversorTest",
      "timeInMs": 3562
    },
    {
      "fullQualifiedName": "org.jsoup.nodes.TextNodeTest",
      "timeInMs": 13603
    },
    {
      "fullQualifiedName": "org.jsoup.parser.TokeniserStateTest",
      "timeInMs": 4358
    },
    {
      "fullQualifiedName": "org.jsoup.integration.ParseTest",
      "timeInMs": 5853
    },
    {
      "fullQualifiedName": "org.jsoup.helper.StringUtilTest",
      "timeInMs": 3436
    },
    {
      "fullQualifiedName": "org.jsoup.helper.W3CDomTest",
      "timeInMs": 207
    },
    {
      "fullQualifiedName": "org.jsoup.nodes.DocumentTypeTest",
      "timeInMs": 4259
    }
  ],
  "projectName": "jsoup_parent"
}